{"Description": "Bitcoin Treasury Holdings (USD) vs Cumulative Market Cap of Public Companies Holding BTC", "Runtime": 1777962096, "Category": "Markets", "Sub": "Crypto Treasuries", "Chart": "Series", "Frequency": "Daily", "Source": "Other", "DailyCheck": false, "yCeiling": null, "yFloor": 0, "reverseYAxis": false, "xAxisType": "Datetime", "Series": {}, "Start": 1439164800, "Slug": "markets_cryptotreasuries_bitcointreasuryholdingsusdvscumulativemarketcapofpubliccompaniesholdingbtc_daily_other", "UpdatedAt": 1777962868}
